psyched/__init__.py
psyched/dag.py
psyched/image.py
psyched/task.py
psyched/task_status.py
src/__init__.py
src/dag.py
src/image.py
src/task.py
src/task_status.py
psyched-0.0.1.dist-info/COPYING
psyched-0.0.1.dist-info/METADATA
psyched-0.0.1.dist-info/WHEEL
psyched-0.0.1.dist-info/top_level.txt
psyched-0.0.1.dist-info/RECORD
