Metadata-Version: 2.1
Name: psyched
Version: 0.0.1
Summary: A docker task scheduling package.
Home-page: https://github.com/joacoib/psyched
Author: Joaquín Ignacio Barotto
Author-email: joaquin.barotto@gmail.com
License: UNKNOWN
Platform: UNKNOWN
Classifier: Programming Language :: Python :: 3
Classifier: Development Status :: 2 - Pre-Alpha
Classifier: Intended Audience :: Developers
Classifier: License :: OSI Approved :: GNU General Public License v3 (GPLv3)
